steam_sdk/__init__.py
steam_sdk/analyses/AnalysisEvent.py
steam_sdk/analyses/AnalysisEventLHC.py
steam_sdk/analyses/AnalysisSTEAM.py
steam_sdk/analyses/__init__.py
steam_sdk/analyses/custom_analyses/__init__.py
steam_sdk/analyses/custom_analyses/analysis_short_circuit_LEDET_1/__init__.py
steam_sdk/analyses/custom_analyses/analysis_short_circuit_LEDET_1/analysis_short_circuit_LEDET_1.py
steam_sdk/analyses/custom_analyses/analysis_short_circuit_LEDET_1/utils/__init__.py
steam_sdk/analyses/custom_analyses/analysis_short_circuit_LEDET_1/utils/calculate_short_parameters.py
steam_sdk/analyses/custom_analyses/analysis_short_circuit_LEDET_1/utils/copy_input_files.py
steam_sdk/analyses/custom_analyses/analysis_short_circuit_LEDET_1/utils/set_common_parameters.py
steam_sdk/analyses/custom_analyses/analysis_short_circuit_LEDET_1/utils/set_magnet_specific_parameters.py
steam_sdk/analyses/custom_analyses/analysis_short_circuit_LEDET_1/utils/set_short_circuit_analysis_parameters.py
steam_sdk/analyses/custom_analyses/analysis_short_circuit_LEDET_1/utils/set_simulations_to_prepare_run.py
steam_sdk/analyses/custom_analyses/co_simulation_QH_PyBBQ_LEDET_1/__init__.py
steam_sdk/analyses/custom_analyses/co_simulation_QH_PyBBQ_LEDET_1/co_simulation_QH_PyBBQ_LEDET_1.py
steam_sdk/analyses/custom_analyses/co_simulation_QH_PyBBQ_LEDET_1/utils/__init__.py
steam_sdk/analyses/custom_analyses/co_simulation_QH_PyBBQ_LEDET_1/utils/calculate_quench_propagation_velocity.py
steam_sdk/analyses/custom_analyses/co_simulation_QH_PyBBQ_LEDET_1/utils/create_conductor_analysis_file.py
steam_sdk/analyses/custom_analyses/co_simulation_QH_PyBBQ_LEDET_1/utils/create_magnet_analysis_file.py
steam_sdk/analyses/custom_analyses/co_simulation_QH_PyBBQ_LEDET_MBRD_validation_1/__init__.py
steam_sdk/analyses/custom_analyses/co_simulation_QH_PyBBQ_LEDET_MBRD_validation_1/co_simulation_QH_PyBBQ_LEDET_MBRD_validation_1.py
steam_sdk/analyses/custom_analyses/co_simulation_QH_PyBBQ_LEDET_MBRD_validation_1/utils/__init__.py
steam_sdk-2026.1.2.dist-info/METADATA
steam_sdk-2026.1.2.dist-info/WHEEL
steam_sdk-2026.1.2.dist-info/top_level.txt
steam_sdk-2026.1.2.dist-info/RECORD
