Metadata-Version: 2.4
Name: steam_sdk
Version: 2026.1.2
Summary: Source code for APIs for STEAM tools.
Home-page: https://gitlab.cern.ch/steam/steam_sdk
Author: STEAM Team
Author-email: steam-team@cern.ch
Keywords: STEAM,API,SDK,CERN
Classifier: Programming Language :: Python :: 3.11
Requires-Python: >=3.11
Requires-Dist: gmsh==4.15.0
Requires-Dist: matplotlib==3.8.3
Requires-Dist: Jinja2==3.1.3
Requires-Dist: numpy==1.26.4
Requires-Dist: pandas==2.2.1
Requires-Dist: pydantic==2.6.4
Requires-Dist: ruamel.yaml==0.18.6
Requires-Dist: scipy==1.14.1
Requires-Dist: deepdiff==6.7.1
Requires-Dist: h5py==3.10.0
Requires-Dist: npTDMS==1.8.0
Requires-Dist: ipython==8.22.2
Requires-Dist: matplotlib-inline==0.1.6
Requires-Dist: openpyxl==3.1.2
Requires-Dist: pysoleno==0.0.8
Requires-Dist: reportlab==4.1.0
Requires-Dist: requests==2.31.0
Requires-Dist: ruamel.yaml.clib==0.2.8
Requires-Dist: seaborn==0.13.2
Requires-Dist: STEAM-materials==2025.6.1
Requires-Dist: steam-magnetic-calculations==0.1
Requires-Dist: svglib==1.5.1
Requires-Dist: PyYAML==6.0.1
Requires-Dist: steam-pysigma==2025.2.0
Requires-Dist: pyarrow==15.0.1
Requires-Dist: tqdm==4.66.2
Requires-Dist: mplcursors==0.5.3
Requires-Dist: numba==0.60.0
Requires-Dist: sympy==1.13.3
Provides-Extra: all
Requires-Dist: gmsh==4.15.0; extra == "all"
Requires-Dist: matplotlib==3.8.3; extra == "all"
Requires-Dist: Jinja2==3.1.3; extra == "all"
Requires-Dist: numpy==1.26.4; extra == "all"
Requires-Dist: pandas==2.2.1; extra == "all"
Requires-Dist: pydantic==2.6.4; extra == "all"
Requires-Dist: ruamel.yaml==0.18.6; extra == "all"
Requires-Dist: scipy==1.14.1; extra == "all"
Requires-Dist: deepdiff==6.7.1; extra == "all"
Requires-Dist: h5py==3.10.0; extra == "all"
Requires-Dist: npTDMS==1.8.0; extra == "all"
Requires-Dist: ipython==8.22.2; extra == "all"
Requires-Dist: matplotlib-inline==0.1.6; extra == "all"
Requires-Dist: openpyxl==3.1.2; extra == "all"
Requires-Dist: pysoleno==0.0.8; extra == "all"
Requires-Dist: reportlab==4.1.0; extra == "all"
Requires-Dist: requests==2.31.0; extra == "all"
Requires-Dist: ruamel.yaml.clib==0.2.8; extra == "all"
Requires-Dist: seaborn==0.13.2; extra == "all"
Requires-Dist: STEAM-materials==2025.6.1; extra == "all"
Requires-Dist: steam-magnetic-calculations==0.1; extra == "all"
Requires-Dist: svglib==1.5.1; extra == "all"
Requires-Dist: PyYAML==6.0.1; extra == "all"
Requires-Dist: steam-pysigma==2025.2.0; extra == "all"
Requires-Dist: pyarrow==15.0.1; extra == "all"
Requires-Dist: tqdm==4.66.2; extra == "all"
Requires-Dist: mplcursors==0.5.3; extra == "all"
Requires-Dist: numba==0.60.0; extra == "all"
Requires-Dist: sympy==1.13.3; extra == "all"
Requires-Dist: Markdown==3.8; extra == "all"
Requires-Dist: markdown-include==0.8.1; extra == "all"
Requires-Dist: MarkupSafe==2.1.5; extra == "all"
Requires-Dist: mkdocs==1.6.1; extra == "all"
Requires-Dist: mkdocs-autorefs==1.4.1; extra == "all"
Requires-Dist: mkdocs-git-revision-date-localized-plugin==1.4.5; extra == "all"
Requires-Dist: mkdocs-include-markdown-plugin==7.1.5; extra == "all"
Requires-Dist: mkdocs-material==9.6.14; extra == "all"
Requires-Dist: mkdocs-material-extensions==1.3.1; extra == "all"
Requires-Dist: mkdocstrings==0.29.0; extra == "all"
Requires-Dist: mkdocstrings-python==1.16.10; extra == "all"
Requires-Dist: Pygments==2.17.2; extra == "all"
Requires-Dist: pymdown-extensions==10.7.1; extra == "all"
Requires-Dist: coverage==7.4.3; extra == "all"
Requires-Dist: coverage-badge==1.1.0; extra == "all"
Requires-Dist: griffe==1.7.3; extra == "all"
Requires-Dist: pytest==8.1.1; extra == "all"
Requires-Dist: pytest-cov==4.1.0; extra == "all"
Requires-Dist: setuptools==69.2.0; extra == "all"
Requires-Dist: twine==6.1.0; extra == "all"
Provides-Extra: docs
Requires-Dist: Markdown==3.8; extra == "docs"
Requires-Dist: markdown-include==0.8.1; extra == "docs"
Requires-Dist: MarkupSafe==2.1.5; extra == "docs"
Requires-Dist: mkdocs==1.6.1; extra == "docs"
Requires-Dist: mkdocs-autorefs==1.4.1; extra == "docs"
Requires-Dist: mkdocs-git-revision-date-localized-plugin==1.4.5; extra == "docs"
Requires-Dist: mkdocs-include-markdown-plugin==7.1.5; extra == "docs"
Requires-Dist: mkdocs-material==9.6.14; extra == "docs"
Requires-Dist: mkdocs-material-extensions==1.3.1; extra == "docs"
Requires-Dist: mkdocstrings==0.29.0; extra == "docs"
Requires-Dist: mkdocstrings-python==1.16.10; extra == "docs"
Requires-Dist: Pygments==2.17.2; extra == "docs"
Requires-Dist: pymdown-extensions==10.7.1; extra == "docs"
Provides-Extra: test
Requires-Dist: coverage==7.4.3; extra == "test"
Requires-Dist: coverage-badge==1.1.0; extra == "test"
Requires-Dist: griffe==1.7.3; extra == "test"
Requires-Dist: pytest==8.1.1; extra == "test"
Requires-Dist: pytest-cov==4.1.0; extra == "test"
Provides-Extra: build
Requires-Dist: setuptools==69.2.0; extra == "build"
Requires-Dist: twine==6.1.0; extra == "build"
Dynamic: author
Dynamic: author-email
Dynamic: classifier
Dynamic: description
Dynamic: description-content-type
Dynamic: home-page
Dynamic: keywords
Dynamic: provides-extra
Dynamic: requires-dist
Dynamic: requires-python
Dynamic: summary
